README.md
setup.py
Flask_EventPlanner.egg-info/PKG-INFO
Flask_EventPlanner.egg-info/SOURCES.txt
Flask_EventPlanner.egg-info/dependency_links.txt
Flask_EventPlanner.egg-info/requires.txt
Flask_EventPlanner.egg-info/top_level.txt
flask_eventplanner/__init__.py
flask_eventplanner/core.py
flask_eventplanner/model.py