Metadata-Version: 2.1
Name: Flask-EventPlanner
Version: 0.3
Summary: Event planner extension for Flask
Home-page: https://github.com/gerelorant/Flask-EventPlanner
Author: Gere Lóránt
Author-email: gerelorant@gmail.com
License: MIT
Platform: UNKNOWN
